xoffice/__init__.py
xoffice/excel.py
xoffice/excel2word.py
xoffice/mail.py
xoffice/pdf.py
xoffice/utils.py
xoffice/word.py
xoffice/example/data.xlsx
xoffice/example/template.docx
xoffice/example/test.md
xoffice/example/pdf-test/001.jpg
xoffice/example/pdf-test/002.png
xoffice/templates/md.css
xoffice-0.0.3.dist-info/METADATA
xoffice-0.0.3.dist-info/WHEEL
xoffice-0.0.3.dist-info/licenses/LICENSE
xoffice-0.0.3.dist-info/RECORD
