Metadata-Version: 2.1
Name: xoffice
Version: 0.0.3
Summary: 办公自动化工具包
Author-email: xue0228 <1174543101@qq.com>
License: The MIT License (MIT)
License-File: LICENSE
Classifier: License :: OSI Approved :: MIT License
Classifier: Operating System :: Microsoft :: Windows
Classifier: Programming Language :: Python :: 3
Requires-Python: >=3.8
Requires-Dist: docx-mailmerge2
Requires-Dist: img2pdf
Requires-Dist: lxml
Requires-Dist: markdown
Requires-Dist: numpy
Requires-Dist: opencv-python
Requires-Dist: pymupdf>1.23.0
Requires-Dist: pywin32
Requires-Dist: toronado
Requires-Dist: tqdm
